Workbook

Sheet Dashboard
B2: 2026 BUDGET PLANNER
B3: Your whole year at a glance — every number updates automatically
B7: TOTAL INCOME | D7: TOTAL EXPENSES | F7: NET SAVED | H7: AVG SAVINGS RATE
B8: ='Annual Summary'!C20 | D8: ='Annual Summary'!D20 | F8: ='Annual Summary'!E20 | H8: ='Annual Summary'!F20
B45: Thank you for supporting PlanaryShop! For personal use only.

Sheet Income
B2: INCOME
B3: Type your income in the white cells — beige cells calculate themselves
B7: INCOME SOURCE | C7: JAN | D7: FEB | E7: MAR | F7: APR | G7: MAY | H7: JUN | I7: JUL | J7: AUG | K7: SEP | L7: OCT | M7: NOV | N7: DEC | O7: TOTAL
B8: Salary | O8: =SUM(C8:N8)
B9: Side hustle | O9: =SUM(C9:N9)
B10: Freelance | O10: =SUM(C10:N10)
B11: Investments | O11: =SUM(C11:N11)
B12: Other | O12: =SUM(C12:N12)
B13: TOTAL | C13: =SUM(C8:C12) | D13: =SUM(D8:D12) | E13: =SUM(E8:E12) | F13: =SUM(F8:F12) | G13: =SUM(G8:G12) | H13: =SUM(H8:H12) | I13: =SUM(I8:I12) | J13: =SUM(J8:J12) | ... O13: =SUM(O8:O12)
B15: Thank you for supporting PlanaryShop! For personal use only.

Sheet Expenses
B2: EXPENSES
B3: Track spending by category — beige cells calculate themselves
B7: CATEGORY | C7: JAN | D7: FEB | E7: MAR | F7: APR | G7: MAY | H7: JUN | I7: JUL | J7: AUG | K7: SEP | L7: OCT | M7: NOV | N7: DEC | O7: TOTAL
B8: Housing | O8: =SUM(C8:N8)
B9: Utilities | O9: =SUM(C9:N9)
B10: Groceries | O10: =SUM(C10:N10)
B11: Transportation | O11: =SUM(C11:N11)
B12: Insurance | O12: =SUM(C12:N12)
B13: Health | O13: =SUM(C13:N13)
B14: Dining Out | O14: =SUM(C14:N14)
B15: Entertainment | O15: =SUM(C15:N15)
B16: Subscriptions | O16: =SUM(C16:N16)
B17: Shopping | O17: =SUM(C17:N17)
B18: Personal Care | O18: =SUM(C18:N18)
B19: Education | O19: =SUM(C19:N19)
... B22: Other | O22: =SUM(C22:N22)
B23: TOTAL | C23: =SUM(C8:C22) | D23: =SUM(D8:D22) | E23: =SUM(E8:E22) | F23: =SUM(F8:F22) | G23: =SUM(G8:G22) | H23: =SUM(H8:H22) | I23: =SUM(I8:I22) | J23: =SUM(J8:J22) | ... O23: =SUM(O8:O22)
B25: Thank you for supporting PlanaryShop! For personal use only.

Sheet Savings
B2: SAVINGS
B3: Set a target, log what you saved — progress fills in on its own
B7: SAVINGS GOAL | C7: TARGET | D7: SAVED | E7: PROGRESS
B8: Emergency fund | E8: =IF(C8=0,0,D8/C8)
B9: Vacation | E9: =IF(C9=0,0,D9/C9)
B10: New car | E10: =IF(C10=0,0,D10/C10)
B11: Home | E11: =IF(C11=0,0,D11/C11)
B12: Other | E12: =IF(C12=0,0,D12/C12)
B15: Thank you for supporting PlanaryShop! For personal use only.

Sheet Debts
B2: DEBTS
B3: List each debt once — the remaining balance updates as you pay
B7: DEBT | C7: STARTING BALANCE | D7: PAID SO FAR | E7: REMAINING
B8: Credit card | E8: =C8-D8
B9: Student loan | E9: =C9-D9
B10: Car loan | E10: =C10-D10
B11: Medical | E11: =C11-D11
B12: Other | E12: =C12-D12
B15: Thank you for supporting PlanaryShop! For personal use only.

Sheet Annual Summary
B2: ANNUAL SUMMARY
B3: Nothing to type here — this page reads from Income and Expenses
B7: MONTH | C7: INCOME | D7: EXPENSES | E7: NET SAVINGS | F7: SAVINGS RATE
B8: JAN | C8: =Income!C13 | D8: =Expenses!C23 | E8: =C8-D8 | F8: =IF(C8=0,0,E8/C8)
B9: FEB | C9: =Income!D13 | D9: =Expenses!D23 | E9: =C9-D9 | F9: =IF(C9=0,0,E9/C9)
B10: MAR | C10: =Income!E13 | D10: =Expenses!E23 | E10: =C10-D10 | F10: =IF(C10=0,0,E10/C10)
B11: APR | C11: =Income!F13 | D11: =Expenses!F23 | E11: =C11-D11 | F11: =IF(C11=0,0,E11/C11)
B12: MAY | C12: =Income!G13 | D12: =Expenses!G23 | E12: =C12-D12 | F12: =IF(C12=0,0,E12/C12)
B13: JUN | C13: =Income!H13 | D13: =Expenses!H23 | E13: =C13-D13 | F13: =IF(C13=0,0,E13/C13)
B14: JUL | C14: =Income!I13 | D14: =Expenses!I23 | E14: =C14-D14 | F14: =IF(C14=0,0,E14/C14)
B15: AUG | C15: =Income!J13 | D15: =Expenses!J23 | E15: =C15-D15 | F15: =IF(C15=0,0,E15/C15)
B16: SEP | C16: =Income!K13 | D16: =Expenses!K23 | E16: =C16-D16 | F16: =IF(C16=0,0,E16/C16)
B17: OCT | C17: =Income!L13 | D17: =Expenses!L23 | E17: =C17-D17 | F17: =IF(C17=0,0,E17/C17)
B18: NOV | C18: =Income!M13 | D18: =Expenses!M23 | E18: =C18-D18 | F18: =IF(C18=0,0,E18/C18)
B19: DEC | C19: =Income!N13 | D19: =Expenses!N23 | E19: =C19-D19 | F19: =IF(C19=0,0,E19/C19)
B20: TOTAL | C20: =SUM(C8:C19) | D20: =SUM(D8:D19) | E20: =SUM(E8:E19) | F20: =IF(C20=0,0,E20/C20)
B22: Thank you for supporting PlanaryShop! For personal use only.
